ds_extraction/__init__.py
ds_extraction/edit_distance.py
ds_extraction/vb_ahocorasick.py
ds_extraction/saved_dict/disease_dict
ds_extraction/saved_dict/symptom_dict
ds_extraction/utils/__init__.py
ds_extraction/utils/preprocess.py
ds_extraction/utils/utils.py
ds_extraction-0.0.3.dist-info/METADATA
ds_extraction-0.0.3.dist-info/WHEEL
ds_extraction-0.0.3.dist-info/top_level.txt
ds_extraction-0.0.3.dist-info/RECORD
